{"": ["aspiration", "hypoxia", "intubation", "chronic_obstructive", "pende", "complain", "liter", "eye", "hemorrhage", "consolidation"], "1-2days jaudice": ["wound", "incision", "final", "chewable", "thicken", "prednisone", "cm", "aortic", "vein", "coumadin"], "66% atypical white blood cells and low platelets on a routine": ["aspiration", "hypoxia", "intubation", "chronic_obstructive", "pende", "complain", "liter", "eye", "hemorrhage", "consolidation"], "abdominal aortic aneurysm": ["wound", "incision", "final", "chewable", "thicken", "prednisone", "cm", "aortic", "vein", "coumadin"], "abdominal pain": ["wound", "incision", "final", "chewable", "thicken", "prednisone", "cm", "aortic", "vein", "coumadin"], "abdominal pain and fever": ["wound", "incision", "final", "chewable", "thicken", "prednisone", "cm", "aortic", "vein", "coumadin"], "abdominal pain and weakness": ["wound", "incision", "final", "chewable", "thicken", "prednisone", "cm", "aortic", "vein", "coumadin"], "abdominal pain transferred from osh": ["wound", "incision", "final", "chewable", "thicken", "prednisone", "cm", "aortic", "vein", "coumadin"], "abnormal outpatient labs": ["wound", "incision", "final", "chewable", "thicken", "prednisone", "cm", "aortic", "vein", "coumadin"], "achyness": ["aspiration", "hypoxia", "intubation", "chronic_obstructive", "pende", "complain", "liter", "eye", "hemorrhage", "consolidation"], "acute blood loss": ["wound", "incision", "final", "chewable", "thicken", "prednisone", "cm", "aortic", "vein", "coumadin"], "acute blood loss anemia due to gastric ulcers with bleeding": ["wound", "incision", "final", "chewable", "thicken", "prednisone", "cm", "aortic", "vein", "coumadin"], "acute mental status": ["aspiration", "hypoxia", "intubation", "chronic_obstructive", "pende", "complain", "liter", "eye", "hemorrhage", "consolidation"], "agitation": ["wound", "incision", "final", "chewable", "thicken", "prednisone", "cm", "aortic", "vein", "coumadin"], "altered mental status": ["wound", "incision", "final", "chewable", "thicken", "prednisone", "cm", "aortic", "vein", "coumadin"], "altered mental status requiring intubation": ["aspiration", "hypoxia", "intubation", "chronic_obstructive", "pende", "complain", "liter", "eye", "hemorrhage", "consolidation"], "altered mental status transfer from micu": ["wound", "incision", "final", "chewable", "thicken", "prednisone", "cm", "aortic", "vein", "coumadin"], "altered ms": ["aspiration", "hypoxia", "intubation", "chronic_obstructive", "pende", "complain", "liter", "eye", "hemorrhage", "consolidation"], "ams": ["wound", "incision", "final", "chewable", "thicken", "prednisone", "cm", "aortic", "vein", "coumadin"], "anemia": ["wound", "incision", "final", "chewable", "thicken", "prednisone", "cm", "aortic", "vein", "coumadin"], "anterior wall stemi": ["wound", "incision", "final", "chewable", "thicken", "prednisone", "cm", "aortic", "vein", "coumadin"], "aortoenteric fistula": ["wound", "incision", "final", "chewable", "thicken", "prednisone", "cm", "aortic", "vein", "coumadin"], "asthma exacerbation": ["wound", "incision", "final", "chewable", "thicken", "prednisone", "cm", "aortic", "vein", "coumadin"], "asymptomatic": ["wound", "incision", "final", "chewable", "thicken", "prednisone", "cm", "aortic", "vein", "coumadin"], "atrial flutter": ["wound", "incision", "final", "chewable", "thicken", "prednisone", "cm", "aortic", "vein", "coumadin"], "back pain": ["wound", "incision", "final", "chewable", "thicken", "prednisone", "cm", "aortic", "vein", "coumadin"], "bacteremia": ["wound", "incision", "final", "chewable", "thicken", "prednisone", "cm", "aortic", "vein", "coumadin"], "bilateral lower extremity dvts": ["aspiration", "hypoxia", "intubation", "chronic_obstructive", "pende", "complain", "liter", "eye", "hemorrhage", "consolidation"], "bilateral mssa empyemas": ["wound", "incision", "final", "chewable", "thicken", "prednisone", "cm", "aortic", "vein", "coumadin"], "biliary colic": ["wound", "incision", "final", "chewable", "thicken", "prednisone", "cm", "aortic", "vein", "coumadin"], "biliary obstuction": ["wound", "incision", "final", "chewable", "thicken", "prednisone", "cm", "aortic", "vein", "coumadin"], "black bowel movement": ["wound", "incision", "final", "chewable", "thicken", "prednisone", "cm", "aortic", "vein", "coumadin"], "bleed tranferred from osh": ["aspiration", "hypoxia", "intubation", "chronic_obstructive", "pende", "complain", "liter", "eye", "hemorrhage", "consolidation"], "bradycardia and hypotension": ["wound", "incision", "final", "chewable", "thicken", "prednisone", "cm", "aortic", "vein", "coumadin"], "brbpr": ["wound", "incision", "final", "chewable", "thicken", "prednisone", "cm", "aortic", "vein", "coumadin"], "brbrp hematuria": ["wound", "incision", "final", "chewable", "thicken", "prednisone", "cm", "aortic", "vein", "coumadin"], "bright red blood per rectum": ["wound", "incision", "final", "chewable", "thicken", "prednisone", "cm", "aortic", "vein", "coumadin"], "cardiogenic shock": ["wound", "incision", "final", "chewable", "thicken", "prednisone", "cm", "aortic", "vein", "coumadin"], "cc:[**cc contact info 104586**]": ["wound", "incision", "final", "chewable", "thicken", "prednisone", "cm", "aortic", "vein", "coumadin"], "chest pain": ["wound", "incision", "final", "chewable", "thicken", "prednisone", "cm", "aortic", "vein", "coumadin"], "chest pain radiating to back and jaw": ["wound", "incision", "final", "chewable", "thicken", "prednisone", "cm", "aortic", "vein", "coumadin"], "chf": ["wound", "incision", "final", "chewable", "thicken", "prednisone", "cm", "aortic", "vein", "coumadin"], "chief complaint:  acute sob": ["wound", "incision", "final", "chewable", "thicken", "prednisone", "cm", "aortic", "vein", "coumadin"], "chief complaint: back pain": ["wound", "incision", "final", "chewable", "thicken", "prednisone", "cm", "aortic", "vein", "coumadin"], "cholelithiasis": ["wound", "incision", "final", "chewable", "thicken", "prednisone", "cm", "aortic", "vein", "coumadin"], "code sepsis": ["wound", "incision", "final", "chewable", "thicken", "prednisone", "cm", "aortic", "vein", "coumadin"], "coffee ground emesis": ["aspiration", "hypoxia", "intubation", "chronic_obstructive", "pende", "complain", "liter", "eye", "hemorrhage", "consolidation"], "concern for proximal airway compression": ["aspiration", "hypoxia", "intubation", "chronic_obstructive", "pende", "complain", "liter", "eye", "hemorrhage", "consolidation"], "concern for status epilepticus": ["wound", "incision", "final", "chewable", "thicken", "prednisone", "cm", "aortic", "vein", "coumadin"], "coronary artery disease": ["wound", "incision", "final", "chewable", "thicken", "prednisone", "cm", "aortic", "vein", "coumadin"], "cough": ["aspiration", "hypoxia", "intubation", "chronic_obstructive", "pende", "complain", "liter", "eye", "hemorrhage", "consolidation"], "critical as": ["wound", "incision", "final", "chewable", "thicken", "prednisone", "cm", "aortic", "vein", "coumadin"], "decreasing hematocrit": ["wound", "incision", "final", "chewable", "thicken", "prednisone", "cm", "aortic", "vein", "coumadin"], "diaphoresis": ["wound", "incision", "final", "chewable", "thicken", "prednisone", "cm", "aortic", "vein", "coumadin"], "diarrhea": ["wound", "incision", "final", "chewable", "thicken", "prednisone", "cm", "aortic", "vein", "coumadin"], "diffuse body pain": ["wound", "incision", "final", "chewable", "thicken", "prednisone", "cm", "aortic", "vein", "coumadin"], "diffuse weakness": ["wound", "incision", "final", "chewable", "thicken", "prednisone", "cm", "aortic", "vein", "coumadin"], "direct admit from osh for transplant work-up": ["wound", "incision", "final", "chewable", "thicken", "prednisone", "cm", "aortic", "vein", "coumadin"], "dizziness": ["wound", "incision", "final", "chewable", "thicken", "prednisone", "cm", "aortic", "vein", "coumadin"], "dka": ["wound", "incision", "final", "chewable", "thicken", "prednisone", "cm", "aortic", "vein", "coumadin"], "dog attack/mauling": ["wound", "incision", "final", "chewable", "thicken", "prednisone", "cm", "aortic", "vein", "coumadin"], "drug ingestion": ["aspiration", "hypoxia", "intubation", "chronic_obstructive", "pende", "complain", "liter", "eye", "hemorrhage", "consolidation"], "duodenal perforation": ["wound", "incision", "final", "chewable", "thicken", "prednisone", "cm", "aortic", "vein", "coumadin"], "dypsnea": ["wound", "incision", "final", "chewable", "thicken", "prednisone", "cm", "aortic", "vein", "coumadin"], "dysarthria and abdominal pain": ["wound", "incision", "final", "chewable", "thicken", "prednisone", "cm", "aortic", "vein", "coumadin"], "dysgerminoma of the right ovary": ["wound", "incision", "final", "chewable", "thicken", "prednisone", "cm", "aortic", "vein", "coumadin"], "dyspnea": ["wound", "incision", "final", "chewable", "thicken", "prednisone", "cm", "aortic", "vein", "coumadin"], "dyspnea and le edema": ["wound", "incision", "final", "chewable", "thicken", "prednisone", "cm", "aortic", "vein", "coumadin"], "dyspnea/ stridor": ["wound", "incision", "final", "chewable", "thicken", "prednisone", "cm", "aortic", "vein", "coumadin"], "echocardiogram showed [**location (un) 109**]=06": ["wound", "incision", "final", "chewable", "thicken", "prednisone", "cm", "aortic", "vein", "coumadin"], "elective admission for stent assisted coiling of acomm aneurysm": ["wound", "incision", "final", "chewable", "thicken", "prednisone", "cm", "aortic", "vein", "coumadin"], "elevated creatinine": ["wound", "incision", "final", "chewable", "thicken", "prednisone", "cm", "aortic", "vein", "coumadin"], "elevated inr": ["wound", "incision", "final", "chewable", "thicken", "prednisone", "cm", "aortic", "vein", "coumadin"], "elevated lfts": ["wound", "incision", "final", "chewable", "thicken", "prednisone", "cm", "aortic", "vein", "coumadin"], "elevated wbc": ["wound", "incision", "final", "chewable", "thicken", "prednisone", "cm", "aortic", "vein", "coumadin"], "epigastric pain": ["wound", "incision", "final", "chewable", "thicken", "prednisone", "cm", "aortic", "vein", "coumadin"], "episodic numbness": ["wound", "incision", "final", "chewable", "thicken", "prednisone", "cm", "aortic", "vein", "coumadin"], "epistaxis": ["wound", "incision", "final", "chewable", "thicken", "prednisone", "cm", "aortic", "vein", "coumadin"], "epistaxis/hemoptysis": ["wound", "incision", "final", "chewable", "thicken", "prednisone", "cm", "aortic", "vein", "coumadin"], "esld secondary to hep c cirrhosis": ["wound", "incision", "final", "chewable", "thicken", "prednisone", "cm", "aortic", "vein", "coumadin"], "fall and increased weight gain": ["wound", "incision", "final", "chewable", "thicken", "prednisone", "cm", "aortic", "vein", "coumadin"], "fall from standing at home": ["wound", "incision", "final", "chewable", "thicken", "prednisone", "cm", "aortic", "vein", "coumadin"], "fall with hematoma to right side of head": ["wound", "incision", "final", "chewable", "thicken", "prednisone", "cm", "aortic", "vein", "coumadin"], "fatigue": ["wound", "incision", "final", "chewable", "thicken", "prednisone", "cm", "aortic", "vein", "coumadin"], "fatigue for one week transferred to ccu with hypoxic distress": ["wound", "incision", "final", "chewable", "thicken", "prednisone", "cm", "aortic", "vein", "coumadin"], "feeling unwell": ["wound", "incision", "final", "chewable", "thicken", "prednisone", "cm", "aortic", "vein", "coumadin"], "fever": ["wound", "incision", "final", "chewable", "thicken", "prednisone", "cm", "aortic", "vein", "coumadin"], "fever and hypotension": ["wound", "incision", "final", "chewable", "thicken", "prednisone", "cm", "aortic", "vein", "coumadin"], "fevers": ["wound", "incision", "final", "chewable", "thicken", "prednisone", "cm", "aortic", "vein", "coumadin"], "fluid overload": ["wound", "incision", "final", "chewable", "thicken", "prednisone", "cm", "aortic", "vein", "coumadin"], "found down [**2193-9-12**]": ["aspiration", "hypoxia", "intubation", "chronic_obstructive", "pende", "complain", "liter", "eye", "hemorrhage", "consolidation"], "free air on cxr": ["wound", "incision", "final", "chewable", "thicken", "prednisone", "cm", "aortic", "vein", "coumadin"], "generalized seizure": ["wound", "incision", "final", "chewable", "thicken", "prednisone", "cm", "aortic", "vein", "coumadin"], "generalized weakness": ["wound", "incision", "final", "chewable", "thicken", "prednisone", "cm", "aortic", "vein", "coumadin"], "gi bleed": ["wound", "incision", "final", "chewable", "thicken", "prednisone", "cm", "aortic", "vein", "coumadin"], "gi bleeding": ["wound", "incision", "final", "chewable", "thicken", "prednisone", "cm", "aortic", "vein", "coumadin"], "gi bleeding/melena": ["wound", "incision", "final", "chewable", "thicken", "prednisone", "cm", "aortic", "vein", "coumadin"], "gib": ["wound", "incision", "final", "chewable", "thicken", "prednisone", "cm", "aortic", "vein", "coumadin"], "hallucinations": ["aspiration", "hypoxia", "intubation", "chronic_obstructive", "pende", "complain", "liter", "eye", "hemorrhage", "consolidation"], "hcc/hcv": ["wound", "incision", "final", "chewable", "thicken", "prednisone", "cm", "aortic", "vein", "coumadin"], "hcc/hcv cirrhosis": ["wound", "incision", "final", "chewable", "thicken", "prednisone", "cm", "aortic", "vein", "coumadin"], "hcv here for liver transplant": ["wound", "incision", "final", "chewable", "thicken", "prednisone", "cm", "aortic", "vein", "coumadin"], "headache": ["wound", "incision", "final", "chewable", "thicken", "prednisone", "cm", "aortic", "vein", "coumadin"], "headaches": ["wound", "incision", "final", "chewable", "thicken", "prednisone", "cm", "aortic", "vein", "coumadin"], "hematemasis": ["wound", "incision", "final", "chewable", "thicken", "prednisone", "cm", "aortic", "vein", "coumadin"], "hematuria": ["aspiration", "hypoxia", "intubation", "chronic_obstructive", "pende", "complain", "liter", "eye", "hemorrhage", "consolidation"], "hemoptysis": ["wound", "incision", "final", "chewable", "thicken", "prednisone", "cm", "aortic", "vein", "coumadin"], "hypercalcemia": ["aspiration", "hypoxia", "intubation", "chronic_obstructive", "pende", "complain", "liter", "eye", "hemorrhage", "consolidation"], "hypertensive urgency": ["wound", "incision", "final", "chewable", "thicken", "prednisone", "cm", "aortic", "vein", "coumadin"], "hypoglycemia": ["wound", "incision", "final", "chewable", "thicken", "prednisone", "cm", "aortic", "vein", "coumadin"], "hyponatremia": ["wound", "incision", "final", "chewable", "thicken", "prednisone", "cm", "aortic", "vein", "coumadin"], "hypopharyngeal mass": ["aspiration", "hypoxia", "intubation", "chronic_obstructive", "pende", "complain", "liter", "eye", "hemorrhage", "consolidation"], "hypotension": ["wound", "incision", "final", "chewable", "thicken", "prednisone", "cm", "aortic", "vein", "coumadin"], "hypotension following anesthesia induction": ["wound", "incision", "final", "chewable", "thicken", "prednisone", "cm", "aortic", "vein", "coumadin"], "hypotension with elevated lactate": ["wound", "incision", "final", "chewable", "thicken", "prednisone", "cm", "aortic", "vein", "coumadin"], "hypothermia": ["wound", "incision", "final", "chewable", "thicken", "prednisone", "cm", "aortic", "vein", "coumadin"], "hypoxia": ["wound", "incision", "final", "chewable", "thicken", "prednisone", "cm", "aortic", "vein", "coumadin"], "hypoxia after ercp": ["wound", "incision", "final", "chewable", "thicken", "prednisone", "cm", "aortic", "vein", "coumadin"], "hypoxia and confusion": ["aspiration", "hypoxia", "intubation", "chronic_obstructive", "pende", "complain", "liter", "eye", "hemorrhage", "consolidation"], "increased frequency of urination": ["wound", "incision", "final", "chewable", "thicken", "prednisone", "cm", "aortic", "vein", "coumadin"], "increased shortness of breath and worsening dysphagia": ["aspiration", "hypoxia", "intubation", "chronic_obstructive", "pende", "complain", "liter", "eye", "hemorrhage", "consolidation"], "infected ppm": ["wound", "incision", "final", "chewable", "thicken", "prednisone", "cm", "aortic", "vein", "coumadin"], "intracerebral hemorrhage (transfer from [**hospital6 204**])": ["aspiration", "hypoxia", "intubation", "chronic_obstructive", "pende", "complain", "liter", "eye", "hemorrhage", "consolidation"], "juxta-renal abdominal aortic aneurysm": ["aspiration", "hypoxia", "intubation", "chronic_obstructive", "pende", "complain", "liter", "eye", "hemorrhage", "consolidation"], "l leg pain and erythema": ["wound", "incision", "final", "chewable", "thicken", "prednisone", "cm", "aortic", "vein", "coumadin"], "labored breathing": ["wound", "incision", "final", "chewable", "thicken", "prednisone", "cm", "aortic", "vein", "coumadin"], "large left temporo-parietal bleed": ["aspiration", "hypoxia", "intubation", "chronic_obstructive", "pende", "complain", "liter", "eye", "hemorrhage", "consolidation"], "leakage of clear fluid from umbilicus": ["wound", "incision", "final", "chewable", "thicken", "prednisone", "cm", "aortic", "vein", "coumadin"], "left foot infection": ["wound", "incision", "final", "chewable", "thicken", "prednisone", "cm", "aortic", "vein", "coumadin"], "lightheadedness": ["wound", "incision", "final", "chewable", "thicken", "prednisone", "cm", "aortic", "vein", "coumadin"], "lithium toxicity": ["wound", "incision", "final", "chewable", "thicken", "prednisone", "cm", "aortic", "vein", "coumadin"], "liver failure": ["wound", "incision", "final", "chewable", "thicken", "prednisone", "cm", "aortic", "vein", "coumadin"], "low back pain": ["wound", "incision", "final", "chewable", "thicken", "prednisone", "cm", "aortic", "vein", "coumadin"], "low hct": ["wound", "incision", "final", "chewable", "thicken", "prednisone", "cm", "aortic", "vein", "coumadin"], "low urine output": ["wound", "incision", "final", "chewable", "thicken", "prednisone", "cm", "aortic", "vein", "coumadin"], "lower gi bleed": ["wound", "incision", "final", "chewable", "thicken", "prednisone", "cm", "aortic", "vein", "coumadin"], "malaise": ["aspiration", "hypoxia", "intubation", "chronic_obstructive", "pende", "complain", "liter", "eye", "hemorrhage", "consolidation"], "melena": ["wound", "incision", "final", "chewable", "thicken", "prednisone", "cm", "aortic", "vein", "coumadin"], "metastatic brain lesions": ["aspiration", "hypoxia", "intubation", "chronic_obstructive", "pende", "complain", "liter", "eye", "hemorrhage", "consolidation"], "methemoglobinemia": ["wound", "incision", "final", "chewable", "thicken", "prednisone", "cm", "aortic", "vein", "coumadin"], "more frequent seizures": ["aspiration", "hypoxia", "intubation", "chronic_obstructive", "pende", "complain", "liter", "eye", "hemorrhage", "consolidation"], "ms [**known lastname 111230**] presented for scheduled laparoscopic bilateral": ["wound", "incision", "final", "chewable", "thicken", "prednisone", "cm", "aortic", "vein", "coumadin"], "mud allohsct": ["wound", "incision", "final", "chewable", "thicken", "prednisone", "cm", "aortic", "vein", "coumadin"], "n/v": ["wound", "incision", "final", "chewable", "thicken", "prednisone", "cm", "aortic", "vein", "coumadin"], "nauesa/vomiting": ["wound", "incision", "final", "chewable", "thicken", "prednisone", "cm", "aortic", "vein", "coumadin"], "nausea": ["wound", "incision", "final", "chewable", "thicken", "prednisone", "cm", "aortic", "vein", "coumadin"], "nausea / vomiting / fatigue": ["aspiration", "hypoxia", "intubation", "chronic_obstructive", "pende", "complain", "liter", "eye", "hemorrhage", "consolidation"], "nausea and mild ruq on palpation on [**2187-8-15**]": ["aspiration", "hypoxia", "intubation", "chronic_obstructive", "pende", "complain", "liter", "eye", "hemorrhage", "consolidation"], "nausea+vomiting": ["aspiration", "hypoxia", "intubation", "chronic_obstructive", "pende", "complain", "liter", "eye", "hemorrhage", "consolidation"], "nausea/emesis": ["aspiration", "hypoxia", "intubation", "chronic_obstructive", "pende", "complain", "liter", "eye", "hemorrhage", "consolidation"], "nausea/vomiting": ["wound", "incision", "final", "chewable", "thicken", "prednisone", "cm", "aortic", "vein", "coumadin"], "nausea/vomiting/diaphoresis": ["wound", "incision", "final", "chewable", "thicken", "prednisone", "cm", "aortic", "vein", "coumadin"], "neck": ["wound", "incision", "final", "chewable", "thicken", "prednisone", "cm", "aortic", "vein", "coumadin"], "neck swelling": ["wound", "incision", "final", "chewable", "thicken", "prednisone", "cm", "aortic", "vein", "coumadin"], "nstemi": ["wound", "incision", "final", "chewable", "thicken", "prednisone", "cm", "aortic", "vein", "coumadin"], "obstructed kidney stone": ["wound", "incision", "final", "chewable", "thicken", "prednisone", "cm", "aortic", "vein", "coumadin"], "obtunded": ["aspiration", "hypoxia", "intubation", "chronic_obstructive", "pende", "complain", "liter", "eye", "hemorrhage", "consolidation"], "odynophagia": ["wound", "incision", "final", "chewable", "thicken", "prednisone", "cm", "aortic", "vein", "coumadin"], "on admission: mr [**known lastname 79336**] states that he experienced two to three": ["wound", "incision", "final", "chewable", "thicken", "prednisone", "cm", "aortic", "vein", "coumadin"], "osh transfer for evaluation and treatment of ttp": ["wound", "incision", "final", "chewable", "thicken", "prednisone", "cm", "aortic", "vein", "coumadin"], "palpitations": ["wound", "incision", "final", "chewable", "thicken", "prednisone", "cm", "aortic", "vein", "coumadin"], "pancreatitis": ["wound", "incision", "final", "chewable", "thicken", "prednisone", "cm", "aortic", "vein", "coumadin"], "pancytopenia": ["aspiration", "hypoxia", "intubation", "chronic_obstructive", "pende", "complain", "liter", "eye", "hemorrhage", "consolidation"], "paraesthesia": ["aspiration", "hypoxia", "intubation", "chronic_obstructive", "pende", "complain", "liter", "eye", "hemorrhage", "consolidation"], "pericardial effusion": ["wound", "incision", "final", "chewable", "thicken", "prednisone", "cm", "aortic", "vein", "coumadin"], "pneumonia": ["wound", "incision", "final", "chewable", "thicken", "prednisone", "cm", "aortic", "vein", "coumadin"], "positive exercise tolerance test": ["wound", "incision", "final", "chewable", "thicken", "prednisone", "cm", "aortic", "vein", "coumadin"], "post atrial ablation": ["wound", "incision", "final", "chewable", "thicken", "prednisone", "cm", "aortic", "vein", "coumadin"], "post-cardiac arrest": ["aspiration", "hypoxia", "intubation", "chronic_obstructive", "pende", "complain", "liter", "eye", "hemorrhage", "consolidation"], "post-op bleeding after tooth extraction": ["wound", "incision", "final", "chewable", "thicken", "prednisone", "cm", "aortic", "vein", "coumadin"], "presyncopal episodes": ["wound", "incision", "final", "chewable", "thicken", "prednisone", "cm", "aortic", "vein", "coumadin"], "productive cough": ["wound", "incision", "final", "chewable", "thicken", "prednisone", "cm", "aortic", "vein", "coumadin"], "pulmonary embolism": ["wound", "incision", "final", "chewable", "thicken", "prednisone", "cm", "aortic", "vein", "coumadin"], "r basilic vein thrombosis": ["wound", "incision", "final", "chewable", "thicken", "prednisone", "cm", "aortic", "vein", "coumadin"], "r-sided weakness and r facial droop": ["aspiration", "hypoxia", "intubation", "chronic_obstructive", "pende", "complain", "liter", "eye", "hemorrhage", "consolidation"], "rash/fever": ["aspiration", "hypoxia", "intubation", "chronic_obstructive", "pende", "complain", "liter", "eye", "hemorrhage", "consolidation"], "renal failure": ["wound", "incision", "final", "chewable", "thicken", "prednisone", "cm", "aortic", "vein", "coumadin"], "renal failure s/p crt": ["aspiration", "hypoxia", "intubation", "chronic_obstructive", "pende", "complain", "liter", "eye", "hemorrhage", "consolidation"], "respiratory depression": ["wound", "incision", "final", "chewable", "thicken", "prednisone", "cm", "aortic", "vein", "coumadin"], "respiratory disress": ["wound", "incision", "final", "chewable", "thicken", "prednisone", "cm", "aortic", "vein", "coumadin"], "respiratory distress": ["wound", "incision", "final", "chewable", "thicken", "prednisone", "cm", "aortic", "vein", "coumadin"], "respiratory distress and chest pain": ["wound", "incision", "final", "chewable", "thicken", "prednisone", "cm", "aortic", "vein", "coumadin"], "respiratory failure": ["wound", "incision", "final", "chewable", "thicken", "prednisone", "cm", "aortic", "vein", "coumadin"], "right adrenal tumor": ["wound", "incision", "final", "chewable", "thicken", "prednisone", "cm", "aortic", "vein", "coumadin"], "right chest pain": ["wound", "incision", "final", "chewable", "thicken", "prednisone", "cm", "aortic", "vein", "coumadin"], "right flank pain": ["wound", "incision", "final", "chewable", "thicken", "prednisone", "cm", "aortic", "vein", "coumadin"], "right knee pain": ["wound", "incision", "final", "chewable", "thicken", "prednisone", "cm", "aortic", "vein", "coumadin"], "right thigh hematoma and decreased urine": ["wound", "incision", "final", "chewable", "thicken", "prednisone", "cm", "aortic", "vein", "coumadin"], "right visual impairment and right eye pain": ["aspiration", "hypoxia", "intubation", "chronic_obstructive", "pende", "complain", "liter", "eye", "hemorrhage", "consolidation"], "rle pain and swelling": ["wound", "incision", "final", "chewable", "thicken", "prednisone", "cm", "aortic", "vein", "coumadin"], "s/p fall": ["wound", "incision", "final", "chewable", "thicken", "prednisone", "cm", "aortic", "vein", "coumadin"], "s/p mvc": ["wound", "incision", "final", "chewable", "thicken", "prednisone", "cm", "aortic", "vein", "coumadin"], "s/p post colonic perforation w/ ileostomy": ["wound", "incision", "final", "chewable", "thicken", "prednisone", "cm", "aortic", "vein", "coumadin"], "s/p recent fall with inability to walk": ["wound", "incision", "final", "chewable", "thicken", "prednisone", "cm", "aortic", "vein", "coumadin"], "s/p unwittnessed fall": ["aspiration", "hypoxia", "intubation", "chronic_obstructive", "pende", "complain", "liter", "eye", "hemorrhage", "consolidation"], "seizure": ["aspiration", "hypoxia", "intubation", "chronic_obstructive", "pende", "complain", "liter", "eye", "hemorrhage", "consolidation"], "seizure and intubated": ["aspiration", "hypoxia", "intubation", "chronic_obstructive", "pende", "complain", "liter", "eye", "hemorrhage", "consolidation"], "seizures": ["aspiration", "hypoxia", "intubation", "chronic_obstructive", "pende", "complain", "liter", "eye", "hemorrhage", "consolidation"], "sepsis": ["wound", "incision", "final", "chewable", "thicken", "prednisone", "cm", "aortic", "vein", "coumadin"], "severe aortic stenosis": ["wound", "incision", "final", "chewable", "thicken", "prednisone", "cm", "aortic", "vein", "coumadin"], "severe ischemia of lower extremities/ s/p r ilio-femoral and": ["wound", "incision", "final", "chewable", "thicken", "prednisone", "cm", "aortic", "vein", "coumadin"], "severe lower extremity lymphedema with superimposed cellulitis": ["wound", "incision", "final", "chewable", "thicken", "prednisone", "cm", "aortic", "vein", "coumadin"], "severe nausea and vomiting": ["wound", "incision", "final", "chewable", "thicken", "prednisone", "cm", "aortic", "vein", "coumadin"], "shortness of breath": ["wound", "incision", "final", "chewable", "thicken", "prednisone", "cm", "aortic", "vein", "coumadin"], "slurred speech": ["wound", "incision", "final", "chewable", "thicken", "prednisone", "cm", "aortic", "vein", "coumadin"], "sob": ["wound", "incision", "final", "chewable", "thicken", "prednisone", "cm", "aortic", "vein", "coumadin"], "status post gastric ulcer perforation": ["wound", "incision", "final", "chewable", "thicken", "prednisone", "cm", "aortic", "vein", "coumadin"], "stridor": ["wound", "incision", "final", "chewable", "thicken", "prednisone", "cm", "aortic", "vein", "coumadin"], "svc thrombosis": ["wound", "incision", "final", "chewable", "thicken", "prednisone", "cm", "aortic", "vein", "coumadin"], "swelling of lips": ["wound", "incision", "final", "chewable", "thicken", "prednisone", "cm", "aortic", "vein", "coumadin"], "syncope": ["aspiration", "hypoxia", "intubation", "chronic_obstructive", "pende", "complain", "liter", "eye", "hemorrhage", "consolidation"], "tachycardia": ["wound", "incision", "final", "chewable", "thicken", "prednisone", "cm", "aortic", "vein", "coumadin"], "thoracic mass": ["wound", "incision", "final", "chewable", "thicken", "prednisone", "cm", "aortic", "vein", "coumadin"], "throat swelling": ["aspiration", "hypoxia", "intubation", "chronic_obstructive", "pende", "complain", "liter", "eye", "hemorrhage", "consolidation"], "thrombocytopenia": ["wound", "incision", "final", "chewable", "thicken", "prednisone", "cm", "aortic", "vein", "coumadin"], "tramatic fx of left fibula": ["wound", "incision", "final", "chewable", "thicken", "prednisone", "cm", "aortic", "vein", "coumadin"], "transfer for management of pancreatitis": ["wound", "incision", "final", "chewable", "thicken", "prednisone", "cm", "aortic", "vein", "coumadin"], "transfer from [**hospital3 **] for variceal bleeding": ["aspiration", "hypoxia", "intubation", "chronic_obstructive", "pende", "complain", "liter", "eye", "hemorrhage", "consolidation"], "transfer from [**hospital3 15174**] for treatment of": ["aspiration", "hypoxia", "intubation", "chronic_obstructive", "pende", "complain", "liter", "eye", "hemorrhage", "consolidation"], "transfer from osh for stemi": ["wound", "incision", "final", "chewable", "thicken", "prednisone", "cm", "aortic", "vein", "coumadin"], "transfer from outside hospital with sepsis and bowel leakage": ["wound", "incision", "final", "chewable", "thicken", "prednisone", "cm", "aortic", "vein", "coumadin"], "transfer to ccu for hypotension status post elective peripheral": ["wound", "incision", "final", "chewable", "thicken", "prednisone", "cm", "aortic", "vein", "coumadin"], "transferred from osh with hypoxic respiratory failure": ["aspiration", "hypoxia", "intubation", "chronic_obstructive", "pende", "complain", "liter", "eye", "hemorrhage", "consolidation"], "trauma:  mvc": ["wound", "incision", "final", "chewable", "thicken", "prednisone", "cm", "aortic", "vein", "coumadin"], "trauma:  stab wound": ["wound", "incision", "final", "chewable", "thicken", "prednisone", "cm", "aortic", "vein", "coumadin"], "ugib": ["wound", "incision", "final", "chewable", "thicken", "prednisone", "cm", "aortic", "vein", "coumadin"], "unresponsive": ["wound", "incision", "final", "chewable", "thicken", "prednisone", "cm", "aortic", "vein", "coumadin"], "unstable angina": ["wound", "incision", "final", "chewable", "thicken", "prednisone", "cm", "aortic", "vein", "coumadin"], "upper gi bleed": ["aspiration", "hypoxia", "intubation", "chronic_obstructive", "pende", "complain", "liter", "eye", "hemorrhage", "consolidation"], "vertigo": ["wound", "incision", "final", "chewable", "thicken", "prednisone", "cm", "aortic", "vein", "coumadin"], "vomiting": ["wound", "incision", "final", "chewable", "thicken", "prednisone", "cm", "aortic", "vein", "coumadin"], "vomitting": ["wound", "incision", "final", "chewable", "thicken", "prednisone", "cm", "aortic", "vein", "coumadin"], "weakness": ["wound", "incision", "final", "chewable", "thicken", "prednisone", "cm", "aortic", "vein", "coumadin"], "weakness all over my body": ["wound", "incision", "final", "chewable", "thicken", "prednisone", "cm", "aortic", "vein", "coumadin"], "weight loss and no appetite": ["wound", "incision", "final", "chewable", "thicken", "prednisone", "cm", "aortic", "vein", "coumadin"], "wheezing and shortness of breath": ["aspiration", "hypoxia", "intubation", "chronic_obstructive", "pende", "complain", "liter", "eye", "hemorrhage", "consolidation"], "worsening speech difficulties and decreased movement of the": ["aspiration", "hypoxia", "intubation", "chronic_obstructive", "pende", "complain", "liter", "eye", "hemorrhage", "consolidation"]}